crownstone_cloud/__init__.py
crownstone_cloud/cloud.py
crownstone_cloud/const.py
crownstone_cloud/exceptions.py
crownstone_cloud/cloud_models/__init__.py
crownstone_cloud/cloud_models/crownstones.py
crownstone_cloud/cloud_models/locations.py
crownstone_cloud/cloud_models/spheres.py
crownstone_cloud/cloud_models/users.py
crownstone_cloud/helpers/__init__.py
crownstone_cloud/helpers/aiohttp_client.py
crownstone_cloud/helpers/conversion.py
crownstone_cloud/helpers/requests.py
crownstone_cloud/util/__init__.py
crownstone_cloud/util/runners.py
crownstone_cloud-1.4.11.dist-info/LICENSE-APACHE
crownstone_cloud-1.4.11.dist-info/LICENSE-LGPL
crownstone_cloud-1.4.11.dist-info/LICENSE-MIT
crownstone_cloud-1.4.11.dist-info/METADATA
crownstone_cloud-1.4.11.dist-info/WHEEL
crownstone_cloud-1.4.11.dist-info/top_level.txt
crownstone_cloud-1.4.11.dist-info/RECORD
